CHANGES.rst
MANIFEST.in
README.md
README.rst
setup.py
iCrawl/__init__.py
iCrawl.egg-info/PKG-INFO
iCrawl.egg-info/SOURCES.txt
iCrawl.egg-info/dependency_links.txt
iCrawl.egg-info/namespace_packages.txt
iCrawl.egg-info/not-zip-safe
iCrawl.egg-info/requires.txt
iCrawl.egg-info/top_level.txt
iCrawl/base/__init__.py
iCrawl/base/handleRequest.py
iCrawl/base/queue.py
iCrawl/base/spider.py
iCrawl/base/work.py
iCrawl/conf/__init__.py
iCrawl/db/__init__.py
iCrawl/db/mongo_handler.py
iCrawl/db/mysql_handler.py
iCrawl/db/mysql_operator.py
iCrawl/excep/__init__.py
iCrawl/excep/mysql_exception.py
iCrawl/excep/other_exception.py
iCrawl/fixture/__init__.py
iCrawl/fixture/key_martix.py
iCrawl/utils/__init__.py
iCrawl/utils/atlas.py
iCrawl/utils/character.py
iCrawl/utils/cmail.py
iCrawl/utils/cmisc.py
iCrawl/utils/cparser.py
iCrawl/utils/cprint.py
iCrawl/utils/protocol.py