Metadata-Version: 1.0
Name: iCrawl
Version: 1.0.6
Summary: iCrawl 
Home-page: http://www.google.com
Author: tasiguo
Author-email: tasiguo@gmail.com
License: UNKNOWN
Keywords: web wbs crawl
Platform: UNKNOWN
